calculator/operations.py
tinyinterrordb-0.1.dist-info/licenses/LICENSE.txt
tinyinterrordb-0.1.dist-info/METADATA
tinyinterrordb-0.1.dist-info/WHEEL
tinyinterrordb-0.1.dist-info/top_level.txt
tinyinterrordb-0.1.dist-info/RECORD
