Metadata-Version: 2.4
Name: tinyintErrorDB
Version: 0.1
Summary: Este paquete nos permite validar errores de tipo tinyInt
Home-page: 
Author: David
Author-email: da.barrios.vargas@gmail.com
Keywords: error,int,tinyInt
License-File: LICENSE.txt
Dynamic: author
Dynamic: author-email
Dynamic: keywords
Dynamic: license-file
Dynamic: summary
